{
  "children":[
    {"children":[{"type":"text","value":"In or to a higher position than something else."}],"type":"paragraph"},
    {"children":[{"type":"text","value":"Usage Examples"}],"depth":2,"type":"heading"},
    {"children":[{"checked":null,"children":[{"children":[{"children":[{"type":"text","value":"桌子上边"}],"type":"strong"},{"type":"text","value":" (zhuōzi shàng biān) - \"on top of the table\""}],"type":"paragraph"}],"spread":false,"type":"listItem"},{"checked":null,"children":[{"children":[{"children":[{"type":"text","value":"楼上边"}],"type":"strong"},{"type":"text","value":" (lóu shàng biān) - \"upstairs\""}],"type":"paragraph"}],"spread":false,"type":"listItem"},{"checked":null,"children":[{"children":[{"children":[{"type":"text","value":"上边写着"}],"type":"strong"},{"type":"text","value":" (shàng biān xiě zhe) - \"written above\""}],"type":"paragraph"}],"spread":false,"type":"listItem"},{"checked":null,"children":[{"children":[{"children":[{"type":"text","value":"看上边"}],"type":"strong"},{"type":"text","value":" (kàn shàng biān) - \"look above\""}],"type":"paragraph"}],"spread":false,"type":"listItem"}],"ordered":false,"spread":false,"start":null,"type":"list"},
    {"children":[{"type":"text","value":"Spatial Reference System"}],"depth":2,"type":"heading"},
    {"children":[{"type":"text","value":"上边 is part of complete directional vocabulary:"}],"type":"paragraph"},
    {"children":[{"checked":null,"children":[{"children":[{"children":[{"type":"text","value":"上边"}],"type":"strong"},{"type":"text","value":" (shàng biān) - above; on top"}],"type":"paragraph"}],"spread":false,"type":"listItem"},{"checked":null,"children":[{"children":[{"children":[{"type":"text","value":"下边"}],"type":"strong"},{"type":"text","value":" (xià biān) - below; underneath"}],"type":"paragraph"}],"spread":false,"type":"listItem"},{"checked":null,"children":[{"children":[{"children":[{"type":"text","value":"左边"}],"type":"strong"},{"type":"text","value":" (zuǒ biān) - left side"}],"type":"paragraph"}],"spread":false,"type":"listItem"},{"checked":null,"children":[{"children":[{"children":[{"type":"text","value":"右边"}],"type":"strong"},{"type":"text","value":" (yòu biān) - right side"}],"type":"paragraph"}],"spread":false,"type":"listItem"},{"checked":null,"children":[{"children":[{"children":[{"type":"text","value":"前边"}],"type":"strong"},{"type":"text","value":" (qián biān) - front"}],"type":"paragraph"}],"spread":false,"type":"listItem"},{"checked":null,"children":[{"children":[{"children":[{"type":"text","value":"后边"}],"type":"strong"},{"type":"text","value":" (hòu biān) - back"}],"type":"paragraph"}],"spread":false,"type":"listItem"}],"ordered":false,"spread":false,"start":null,"type":"list"},
    {"children":[{"type":"text","value":"Grammar Patterns"}],"depth":2,"type":"heading"},
    {"children":[{"type":"text","value":"上边 functions as a "},{"children":[{"type":"text","value":"location noun"}],"type":"strong"},{"type":"text","value":":"}],"type":"paragraph"},
    {"children":[{"checked":null,"children":[{"children":[{"children":[{"type":"text","value":"在 + [noun] + 上边"}],"type":"strong"},{"type":"text","value":": on top of + [noun]"}],"type":"paragraph"}],"spread":false,"type":"listItem"},{"checked":null,"children":[{"children":[{"children":[{"type":"text","value":"从上边"}],"type":"strong"},{"type":"text","value":": from above"}],"type":"paragraph"}],"spread":false,"type":"listItem"},{"checked":null,"children":[{"children":[{"children":[{"type":"text","value":"往上边"}],"type":"strong"},{"type":"text","value":": toward the upper area"}],"type":"paragraph"}],"spread":false,"type":"listItem"},{"checked":null,"children":[{"children":[{"children":[{"type":"text","value":"上边的"}],"type":"strong"},{"type":"text","value":": the one(s) above"}],"type":"paragraph"}],"spread":false,"type":"listItem"}],"ordered":false,"spread":false,"start":null,"type":"list"},
    {"children":[{"type":"text","value":"Spatial Cognition"}],"depth":2,"type":"heading"},
    {"children":[{"type":"text","value":"上边 helps organize spatial understanding:"}],"type":"paragraph"},
    {"children":[{"checked":null,"children":[{"children":[{"children":[{"type":"text","value":"Vertical positioning"}],"type":"strong"},{"type":"text","value":": Understanding height relationships"}],"type":"paragraph"}],"spread":false,"type":"listItem"},{"checked":null,"children":[{"children":[{"children":[{"type":"text","value":"Reference framework"}],"type":"strong"},{"type":"text","value":": Creating mental spatial maps"}],"type":"paragraph"}],"spread":false,"type":"listItem"},{"checked":null,"children":[{"children":[{"children":[{"type":"text","value":"Object location"}],"type":"strong"},{"type":"text","value":": Describing where things are positioned"}],"type":"paragraph"}],"spread":false,"type":"listItem"},{"checked":null,"children":[{"children":[{"children":[{"type":"text","value":"Direction giving"}],"type":"strong"},{"type":"text","value":": Helping others navigate space"}],"type":"paragraph"}],"spread":false,"type":"listItem"}],"ordered":false,"spread":false,"start":null,"type":"list"},
    {"children":[{"type":"text","value":"Cultural Context"}],"depth":2,"type":"heading"},
    {"children":[{"type":"text","value":"上边 reflects Chinese spatial thinking:"}],"type":"paragraph"},
    {"children":[{"checked":null,"children":[{"children":[{"children":[{"type":"text","value":"Hierarchy awareness"}],"type":"strong"},{"type":"text","value":": Higher positions often signify importance"}],"type":"paragraph"}],"spread":false,"type":"listItem"},{"checked":null,"children":[{"children":[{"children":[{"type":"text","value":"Feng shui principles"}],"type":"strong"},{"type":"text","value":": Spatial arrangement affects harmony"}],"type":"paragraph"}],"spread":false,"type":"listItem"},{"checked":null,"children":[{"children":[{"children":[{"type":"text","value":"Practical navigation"}],"type":"strong"},{"type":"text","value":": Essential for describing physical relationships"}],"type":"paragraph"}],"spread":false,"type":"listItem"},{"checked":null,"children":[{"children":[{"children":[{"type":"text","value":"Respectful positioning"}],"type":"strong"},{"type":"text","value":": Understanding proper spatial etiquette"}],"type":"paragraph"}],"spread":false,"type":"listItem"}],"ordered":false,"spread":false,"start":null,"type":"list"},
    {"children":[{"type":"text","value":"The concept embodies systematic approach to describing spatial relationships in Chinese culture."}],"type":"paragraph"}
  ],
  "type":"root"
}