{
  "children":[
    {"children":[{"type":"text","value":"To leave or descend from a vehicle."}],"type":"paragraph"},
    {"children":[{"type":"text","value":"Usage Examples"}],"depth":2,"type":"heading"},
    {"children":[{"checked":null,"children":[{"children":[{"children":[{"type":"text","value":"该下车了"}],"type":"strong"},{"type":"text","value":" (gāi xià chē le) - \"time to get off\""}],"type":"paragraph"}],"spread":false,"type":"listItem"},{"checked":null,"children":[{"children":[{"children":[{"type":"text","value":"下车了"}],"type":"strong"},{"type":"text","value":" (xià chē le) - \"got off the vehicle\""}],"type":"paragraph"}],"spread":false,"type":"listItem"},{"checked":null,"children":[{"children":[{"children":[{"type":"text","value":"准备下车"}],"type":"strong"},{"type":"text","value":" (zhǔnbèi xià chē) - \"prepare to get off\""}],"type":"paragraph"}],"spread":false,"type":"listItem"},{"checked":null,"children":[{"children":[{"children":[{"type":"text","value":"下车小心"}],"type":"strong"},{"type":"text","value":" (xià chē xiǎoxīn) - \"be careful getting off\""}],"type":"paragraph"}],"spread":false,"type":"listItem"}],"ordered":false,"spread":false,"start":null,"type":"list"},
    {"children":[{"type":"text","value":"Transportation Contexts"}],"depth":2,"type":"heading"},
    {"children":[{"type":"text","value":"下车 applies to various vehicles:"}],"type":"paragraph"},
    {"children":[{"checked":null,"children":[{"children":[{"children":[{"type":"text","value":"下公交车"}],"type":"strong"},{"type":"text","value":" (xià gōngjiāo chē) - get off the bus"}],"type":"paragraph"}],"spread":false,"type":"listItem"},{"checked":null,"children":[{"children":[{"children":[{"type":"text","value":"下地铁"}],"type":"strong"},{"type":"text","value":" (xià dìtiě) - exit the subway"}],"type":"paragraph"}],"spread":false,"type":"listItem"},{"checked":null,"children":[{"children":[{"children":[{"type":"text","value":"下火车"}],"type":"strong"},{"type":"text","value":" (xià huǒchē) - get off the train"}],"type":"paragraph"}],"spread":false,"type":"listItem"},{"checked":null,"children":[{"children":[{"children":[{"type":"text","value":"下出租车"}],"type":"strong"},{"type":"text","value":" (xià chūzū chē) - get out of a taxi"}],"type":"paragraph"}],"spread":false,"type":"listItem"}],"ordered":false,"spread":false,"start":null,"type":"list"},
    {"children":[{"type":"text","value":"Transportation Pair"}],"depth":2,"type":"heading"},
    {"children":[{"type":"text","value":"下车 completes the boarding cycle:"}],"type":"paragraph"},
    {"children":[{"checked":null,"children":[{"children":[{"children":[{"type":"text","value":"上车"}],"type":"strong"},{"type":"text","value":" (shàng chē) - get on/board"}],"type":"paragraph"}],"spread":false,"type":"listItem"},{"checked":null,"children":[{"children":[{"children":[{"type":"text","value":"下车"}],"type":"strong"},{"type":"text","value":" (xià chē) - get off/alight"}],"type":"paragraph"}],"spread":false,"type":"listItem"},{"checked":null,"children":[{"children":[{"type":"text","value":"Essential pair for complete transportation journey"}],"type":"paragraph"}],"spread":false,"type":"listItem"}],"ordered":false,"spread":false,"start":null,"type":"list"},
    {"children":[{"type":"text","value":"Grammar Patterns"}],"depth":2,"type":"heading"},
    {"children":[{"type":"text","value":"下车 functions as an "},{"children":[{"type":"text","value":"intransitive verb"}],"type":"strong"},{"type":"text","value":":"}],"type":"paragraph"},
    {"children":[{"checked":null,"children":[{"children":[{"children":[{"type":"text","value":"要下车了"}],"type":"strong"},{"type":"text","value":": about to get off"}],"type":"paragraph"}],"spread":false,"type":"listItem"},{"checked":null,"children":[{"children":[{"children":[{"type":"text","value":"正在下车"}],"type":"strong"},{"type":"text","value":": currently getting off"}],"type":"paragraph"}],"spread":false,"type":"listItem"},{"checked":null,"children":[{"children":[{"children":[{"type":"text","value":"下车以后"}],"type":"strong"},{"type":"text","value":": after getting off"}],"type":"paragraph"}],"spread":false,"type":"listItem"},{"checked":null,"children":[{"children":[{"children":[{"type":"text","value":"下车的时候"}],"type":"strong"},{"type":"text","value":": when getting off"}],"type":"paragraph"}],"spread":false,"type":"listItem"}],"ordered":false,"spread":false,"start":null,"type":"list"},
    {"children":[{"type":"text","value":"Journey Completion"}],"depth":2,"type":"heading"},
    {"children":[{"type":"text","value":"下车 represents destination arrival:"}],"type":"paragraph"},
    {"children":[{"checked":null,"children":[{"children":[{"children":[{"type":"text","value":"Arrival marker"}],"type":"strong"},{"type":"text","value":": Signals end of transportation segment"}],"type":"paragraph"}],"spread":false,"type":"listItem"},{"checked":null,"children":[{"children":[{"children":[{"type":"text","value":"Destination reaching"}],"type":"strong"},{"type":"text","value":": Achievement of travel goal"}],"type":"paragraph"}],"spread":false,"type":"listItem"},{"checked":null,"children":[{"children":[{"children":[{"type":"text","value":"Safety transition"}],"type":"strong"},{"type":"text","value":": Moving from vehicle to pedestrian status"}],"type":"paragraph"}],"spread":false,"type":"listItem"},{"checked":null,"children":[{"children":[{"children":[{"type":"text","value":"Next activity"}],"type":"strong"},{"type":"text","value":": Preparation for post-transportation activities"}],"type":"paragraph"}],"spread":false,"type":"listItem"}],"ordered":false,"spread":false,"start":null,"type":"list"},
    {"children":[{"type":"text","value":"Cultural Context"}],"depth":2,"type":"heading"},
    {"children":[{"type":"text","value":"下车 reflects Chinese transportation etiquette:"}],"type":"paragraph"},
    {"children":[{"checked":null,"children":[{"children":[{"children":[{"type":"text","value":"Orderly alighting"}],"type":"strong"},{"type":"text","value":": Organized exit prevents confusion"}],"type":"paragraph"}],"spread":false,"type":"listItem"},{"checked":null,"children":[{"children":[{"children":[{"type":"text","value":"Safety awareness"}],"type":"strong"},{"type":"text","value":": Careful exit protects all passengers"}],"type":"paragraph"}],"spread":false,"type":"listItem"},{"checked":null,"children":[{"children":[{"children":[{"type":"text","value":"Efficiency maintenance"}],"type":"strong"},{"type":"text","value":": Quick alighting keeps schedules on time"}],"type":"paragraph"}],"spread":false,"type":"listItem"},{"checked":null,"children":[{"children":[{"children":[{"type":"text","value":"Courtesy practice"}],"type":"strong"},{"type":"text","value":": Letting others exit first shows politeness"}],"type":"paragraph"}],"spread":false,"type":"listItem"}],"ordered":false,"spread":false,"start":null,"type":"list"},
    {"children":[{"type":"text","value":"The concept embodies the civilized completion of shared transportation experiences."}],"type":"paragraph"}
  ],
  "type":"root"
}