{
  "children":[
    {"children":[{"type":"text","value":"To successfully deal with or gain control of something difficult; to overcome; to conquer."}],"type":"paragraph"},
    {"children":[{"type":"text","value":"Usage Examples"}],"depth":2,"type":"heading"},
    {"children":[{"checked":null,"children":[{"children":[{"children":[{"type":"text","value":"克服困难"}],"type":"strong"},{"type":"text","value":" (kè fú kùn nan) - \"overcome difficulties\""}],"type":"paragraph"}],"spread":false,"type":"listItem"},{"checked":null,"children":[{"children":[{"children":[{"type":"text","value":"克服恐惧"}],"type":"strong"},{"type":"text","value":" (kè fú kǒng jù) - \"overcome fear\""}],"type":"paragraph"}],"spread":false,"type":"listItem"},{"checked":null,"children":[{"children":[{"children":[{"type":"text","value":"克服缺点"}],"type":"strong"},{"type":"text","value":" (kè fú quē diǎn) - \"overcome shortcomings\""}],"type":"paragraph"}],"spread":false,"type":"listItem"},{"checked":null,"children":[{"children":[{"children":[{"type":"text","value":"努力克服"}],"type":"strong"},{"type":"text","value":" (nǔ lì kè fú) - \"work hard to overcome\""}],"type":"paragraph"}],"spread":false,"type":"listItem"},{"checked":null,"children":[{"children":[{"children":[{"type":"text","value":"克服障碍"}],"type":"strong"},{"type":"text","value":" (kè fú zhàng ài) - \"overcome obstacles\""}],"type":"paragraph"}],"spread":false,"type":"listItem"}],"ordered":false,"spread":false,"start":null,"type":"list"},
    {"children":[{"type":"text","value":"Grammar Patterns"}],"depth":2,"type":"heading"},
    {"children":[{"checked":null,"children":[{"children":[{"children":[{"type":"text","value":"克服 + noun"}],"type":"strong"},{"type":"text","value":" - \"overcome [something]\""}],"type":"paragraph"}],"spread":false,"type":"listItem"},{"checked":null,"children":[{"children":[{"children":[{"type":"text","value":"努力 + 克服"}],"type":"strong"},{"type":"text","value":" - \"work hard to overcome\""}],"type":"paragraph"}],"spread":false,"type":"listItem"},{"checked":null,"children":[{"children":[{"children":[{"type":"text","value":"想办法 + 克服"}],"type":"strong"},{"type":"text","value":" - \"find ways to overcome\""}],"type":"paragraph"}],"spread":false,"type":"listItem"},{"checked":null,"children":[{"children":[{"children":[{"type":"text","value":"帮助...克服"}],"type":"strong"},{"type":"text","value":" - \"help [someone] overcome\""}],"type":"paragraph"}],"spread":false,"type":"listItem"}],"ordered":false,"spread":false,"start":null,"type":"list"},
    {"children":[{"type":"text","value":"Common Collocations"}],"depth":2,"type":"heading"},
    {"children":[{"checked":null,"children":[{"children":[{"children":[{"type":"text","value":"克服困难"}],"type":"strong"},{"type":"text","value":" - overcome difficulties"}],"type":"paragraph"}],"spread":false,"type":"listItem"},{"checked":null,"children":[{"children":[{"children":[{"type":"text","value":"克服恐惧"}],"type":"strong"},{"type":"text","value":" - overcome fear"}],"type":"paragraph"}],"spread":false,"type":"listItem"},{"checked":null,"children":[{"children":[{"children":[{"type":"text","value":"克服缺点"}],"type":"strong"},{"type":"text","value":" - overcome shortcomings"}],"type":"paragraph"}],"spread":false,"type":"listItem"},{"checked":null,"children":[{"children":[{"children":[{"type":"text","value":"克服挑战"}],"type":"strong"},{"type":"text","value":" - overcome challenges"}],"type":"paragraph"}],"spread":false,"type":"listItem"},{"checked":null,"children":[{"children":[{"children":[{"type":"text","value":"克服障碍"}],"type":"strong"},{"type":"text","value":" - overcome obstacles"}],"type":"paragraph"}],"spread":false,"type":"listItem"}],"ordered":false,"spread":false,"start":null,"type":"list"},
    {"children":[{"type":"text","value":"Cultural Context"}],"depth":2,"type":"heading"},
    {"children":[{"type":"text","value":"克服 embodies important Chinese values about perseverance:"}],"type":"paragraph"},
    {"children":[{"checked":null,"children":[{"children":[{"children":[{"type":"text","value":"Self-improvement"}],"type":"strong"},{"type":"text","value":": Overcoming personal weaknesses is highly valued"}],"type":"paragraph"}],"spread":false,"type":"listItem"},{"checked":null,"children":[{"children":[{"children":[{"type":"text","value":"Resilience"}],"type":"strong"},{"type":"text","value":": The ability to 克服 hardships is seen as character-building"}],"type":"paragraph"}],"spread":false,"type":"listItem"},{"checked":null,"children":[{"children":[{"children":[{"type":"text","value":"Collective effort"}],"type":"strong"},{"type":"text","value":": Often used in contexts of national or group challenges"}],"type":"paragraph"}],"spread":false,"type":"listItem"},{"checked":null,"children":[{"children":[{"children":[{"type":"text","value":"Educational philosophy"}],"type":"strong"},{"type":"text","value":": Students are encouraged to 克服学习困难 (overcome learning\ndifficulties)"}],"type":"paragraph"}],"spread":false,"type":"listItem"},{"checked":null,"children":[{"children":[{"children":[{"type":"text","value":"Personal growth"}],"type":"strong"},{"type":"text","value":": 克服 is essential for moral and spiritual development"}],"type":"paragraph"}],"spread":false,"type":"listItem"}],"ordered":false,"spread":false,"start":null,"type":"list"}
  ],
  "type":"root"
}