{
  "children":[
    {"children":[{"type":"text","value":"Core Meaning & Usage"}],"depth":2,"type":"heading"},
    {"children":[{"type":"text","value":"四 represents "},{"children":[{"type":"text","value":"the number four, quartets, and quadruple concepts"}],"type":"strong"},{"type":"text","value":". It's used:"}],"type":"paragraph"},
    {"children":[{"checked":null,"children":[{"children":[{"children":[{"type":"text","value":"As a number"}],"type":"strong"},{"type":"text","value":": 四个季节 (sì gè jìjié) - \"four seasons\""}],"type":"paragraph"}],"spread":false,"type":"listItem"},{"checked":null,"children":[{"children":[{"children":[{"type":"text","value":"In compounds"}],"type":"strong"},{"type":"text","value":": 四月 (sì yuè) - \"April\""}],"type":"paragraph"}],"spread":false,"type":"listItem"},{"checked":null,"children":[{"children":[{"children":[{"type":"text","value":"For ordering"}],"type":"strong"},{"type":"text","value":": 第四 (dì sì) - \"fourth; number four\""}],"type":"paragraph"}],"spread":false,"type":"listItem"},{"checked":null,"children":[{"children":[{"children":[{"type":"text","value":"In directions"}],"type":"strong"},{"type":"text","value":": 四方 (sì fāng) - \"four directions; all around\""}],"type":"paragraph"}],"spread":false,"type":"listItem"}],"ordered":true,"spread":false,"start":1,"type":"list"},
    {"children":[{"type":"text","value":"Examples"}],"depth":2,"type":"heading"},
    {"children":[{"checked":null,"children":[{"children":[{"children":[{"type":"text","value":"四十"}],"type":"strong"},{"type":"text","value":" (sì shí) - \"forty\""}],"type":"paragraph"}],"spread":false,"type":"listItem"},{"checked":null,"children":[{"children":[{"children":[{"type":"text","value":"四川"}],"type":"strong"},{"type":"text","value":" (Sìchuān) - \"Sichuan Province\" (literally \"four rivers\")"}],"type":"paragraph"}],"spread":false,"type":"listItem"},{"checked":null,"children":[{"children":[{"children":[{"type":"text","value":"四季"}],"type":"strong"},{"type":"text","value":" (sì jì) - \"four seasons\""}],"type":"paragraph"}],"spread":false,"type":"listItem"},{"checked":null,"children":[{"children":[{"children":[{"type":"text","value":"星期四"}],"type":"strong"},{"type":"text","value":" (xīngqī sì) - \"Thursday\""}],"type":"paragraph"}],"spread":false,"type":"listItem"}],"ordered":false,"spread":false,"start":null,"type":"list"},
    {"children":[{"type":"text","value":"Cultural Notes"}],"depth":2,"type":"heading"},
    {"children":[{"type":"text","value":"In Chinese culture, four (四) has complex associations:"}],"type":"paragraph"},
    {"children":[{"checked":null,"children":[{"children":[{"children":[{"type":"text","value":"Positive"}],"type":"strong"},{"type":"text","value":": Represents stability, completeness (four directions, four seasons)"}],"type":"paragraph"}],"spread":false,"type":"listItem"},{"checked":null,"children":[{"children":[{"children":[{"type":"text","value":"Superstition"}],"type":"strong"},{"type":"text","value":": Some avoid 四 because it sounds similar to 死 (sǐ, \"death\")"}],"type":"paragraph"}],"spread":false,"type":"listItem"},{"checked":null,"children":[{"children":[{"children":[{"type":"text","value":"Traditional concepts"}],"type":"strong"},{"type":"text","value":": Four cardinal directions, four elements, etc."}],"type":"paragraph"}],"spread":false,"type":"listItem"}],"ordered":false,"spread":false,"start":null,"type":"list"},
    {"children":[{"type":"text","value":"Learning Notes"}],"depth":2,"type":"heading"},
    {"children":[{"type":"text","value":"四 is essential for:"}],"type":"paragraph"},
    {"children":[{"checked":null,"children":[{"children":[{"type":"text","value":"All numbers from 14-19, 40-49, etc."}],"type":"paragraph"}],"spread":false,"type":"listItem"},{"checked":null,"children":[{"children":[{"type":"text","value":"Directional concepts"}],"type":"paragraph"}],"spread":false,"type":"listItem"},{"checked":null,"children":[{"children":[{"type":"text","value":"Time and seasonal expressions"}],"type":"paragraph"}],"spread":false,"type":"listItem"},{"checked":null,"children":[{"children":[{"type":"text","value":"Geographic and architectural terms"}],"type":"paragraph"}],"spread":false,"type":"listItem"}],"ordered":false,"spread":false,"start":null,"type":"list"},
    {"children":[{"type":"text","value":"Unlike 一、二、三 which follow a simple stacking pattern, 四 introduces the concept of enclosed\ncharacters, preparing you for more complex character structures."}],"type":"paragraph"}
  ],
  "type":"root"
}