{
  "children":[
    {"children":[{"type":"text","value":"Refers to the day before today; the previous day; the day that just passed."}],"type":"paragraph"},
    {"children":[{"type":"text","value":"Word Breakdown"}],"depth":2,"type":"heading"},
    {"children":[{"type":"text","value":"昨天 combines concepts of immediate past and day to represent yesterday."}],"type":"paragraph"},
    {"align":[],"children":[{"children":[{"children":[{"type":"text","value":"Component"}],"type":"tableCell"},{"children":[{"type":"text","value":"Meaning"}],"type":"tableCell"}],"type":"tableRow"},{"children":[{"children":[{"children":[{"type":"text","value":"昨"}],"type":"strong"}],"type":"tableCell"},{"children":[{"type":"text","value":"Yesterday; just past - containing 日 (sun/day)"}],"type":"tableCell"}],"type":"tableRow"},{"children":[{"children":[{"children":[{"type":"text","value":"天"}],"type":"strong"}],"type":"tableCell"},{"children":[{"type":"text","value":"Day; sky; heaven - representing the time period"}],"type":"tableCell"}],"type":"tableRow"}],"type":"table"},
    {"children":[{"type":"text","value":"Together they create: \"the day that just passed\" or \"the immediate past day\" - the 24-hour period\nbefore today."}],"type":"paragraph"},
    {"children":[{"type":"text","value":"Core Meaning & Usage"}],"depth":2,"type":"heading"},
    {"children":[{"type":"text","value":"昨天 represents "},{"children":[{"type":"text","value":"the day immediately before today"}],"type":"strong"},{"type":"text","value":". It's used:"}],"type":"paragraph"},
    {"children":[{"checked":null,"children":[{"children":[{"children":[{"type":"text","value":"Time reference"}],"type":"strong"},{"type":"text","value":": 昨天晚上 (zuótiān wǎnshang) - \"last night\""}],"type":"paragraph"}],"spread":false,"type":"listItem"},{"checked":null,"children":[{"children":[{"children":[{"type":"text","value":"Past events"}],"type":"strong"},{"type":"text","value":": 昨天下雨了 (zuótiān xiàyǔ le) - \"it rained yesterday\""}],"type":"paragraph"}],"spread":false,"type":"listItem"},{"checked":null,"children":[{"children":[{"children":[{"type":"text","value":"Recent activities"}],"type":"strong"},{"type":"text","value":": 昨天的工作 (zuótiān de gōngzuò) - \"yesterday's work\""}],"type":"paragraph"}],"spread":false,"type":"listItem"},{"checked":null,"children":[{"children":[{"children":[{"type":"text","value":"Temporal comparison"}],"type":"strong"},{"type":"text","value":": 比昨天好 (bǐ zuótiān hǎo) - \"better than yesterday\""}],"type":"paragraph"}],"spread":false,"type":"listItem"}],"ordered":true,"spread":false,"start":1,"type":"list"},
    {"children":[{"type":"text","value":"Examples"}],"depth":2,"type":"heading"},
    {"children":[{"checked":null,"children":[{"children":[{"children":[{"type":"text","value":"昨天早上"}],"type":"strong"},{"type":"text","value":" (zuótiān zǎoshang) - \"yesterday morning\""}],"type":"paragraph"}],"spread":false,"type":"listItem"},{"checked":null,"children":[{"children":[{"children":[{"type":"text","value":"昨天下午"}],"type":"strong"},{"type":"text","value":" (zuótiān xiàwǔ) - \"yesterday afternoon\""}],"type":"paragraph"}],"spread":false,"type":"listItem"},{"checked":null,"children":[{"children":[{"children":[{"type":"text","value":"昨天晚上"}],"type":"strong"},{"type":"text","value":" (zuótiān wǎnshang) - \"last night\""}],"type":"paragraph"}],"spread":false,"type":"listItem"},{"checked":null,"children":[{"children":[{"children":[{"type":"text","value":"昨天的事"}],"type":"strong"},{"type":"text","value":" (zuótiān de shì) - \"yesterday's events\""}],"type":"paragraph"}],"spread":false,"type":"listItem"},{"checked":null,"children":[{"children":[{"children":[{"type":"text","value":"从昨天开始"}],"type":"strong"},{"type":"text","value":" (cóng zuótiān kāishǐ) - \"since yesterday\""}],"type":"paragraph"}],"spread":false,"type":"listItem"}],"ordered":false,"spread":false,"start":null,"type":"list"},
    {"children":[{"type":"text","value":"Time Periods"}],"depth":2,"type":"heading"},
    {"children":[{"type":"text","value":"昨天 with specific times:"}],"type":"paragraph"},
    {"children":[{"checked":null,"children":[{"children":[{"children":[{"type":"text","value":"昨天凌晨"}],"type":"strong"},{"type":"text","value":" (zuótiān língchén) - \"yesterday dawn\""}],"type":"paragraph"}],"spread":false,"type":"listItem"},{"checked":null,"children":[{"children":[{"children":[{"type":"text","value":"昨天中午"}],"type":"strong"},{"type":"text","value":" (zuótiān zhōngwǔ) - \"yesterday noon\""}],"type":"paragraph"}],"spread":false,"type":"listItem"},{"checked":null,"children":[{"children":[{"children":[{"type":"text","value":"昨天傍晚"}],"type":"strong"},{"type":"text","value":" (zuótiān bàngwǎn) - \"yesterday evening\""}],"type":"paragraph"}],"spread":false,"type":"listItem"},{"checked":null,"children":[{"children":[{"children":[{"type":"text","value":"昨天深夜"}],"type":"strong"},{"type":"text","value":" (zuótiān shēnyè) - \"yesterday late night\""}],"type":"paragraph"}],"spread":false,"type":"listItem"}],"ordered":false,"spread":false,"start":null,"type":"list"},
    {"children":[{"type":"text","value":"Recent Past"}],"depth":2,"type":"heading"},
    {"children":[{"type":"text","value":"昨天 in temporal context:"}],"type":"paragraph"},
    {"children":[{"checked":null,"children":[{"children":[{"children":[{"type":"text","value":"就在昨天"}],"type":"strong"},{"type":"text","value":" (jiù zài zuótiān) - \"just yesterday\""}],"type":"paragraph"}],"spread":false,"type":"listItem"},{"checked":null,"children":[{"children":[{"children":[{"type":"text","value":"昨天才"}],"type":"strong"},{"type":"text","value":" (zuótiān cái) - \"only yesterday\""}],"type":"paragraph"}],"spread":false,"type":"listItem"},{"checked":null,"children":[{"children":[{"children":[{"type":"text","value":"直到昨天"}],"type":"strong"},{"type":"text","value":" (zhídào zuótiān) - \"until yesterday\""}],"type":"paragraph"}],"spread":false,"type":"listItem"},{"checked":null,"children":[{"children":[{"children":[{"type":"text","value":"昨天以前"}],"type":"strong"},{"type":"text","value":" (zuótiān yǐqián) - \"before yesterday\""}],"type":"paragraph"}],"spread":false,"type":"listItem"}],"ordered":false,"spread":false,"start":null,"type":"list"},
    {"children":[{"type":"text","value":"Cultural Context"}],"depth":2,"type":"heading"},
    {"children":[{"type":"text","value":"昨天 in Chinese culture represents:"}],"type":"paragraph"},
    {"children":[{"children":[{"type":"text","value":"Reflection and Learning:"}],"type":"strong"}],"type":"paragraph"},
    {"children":[{"checked":null,"children":[{"children":[{"children":[{"type":"text","value":"昨日之事"}],"type":"strong"},{"type":"text","value":" (zuórì zhī shì) - \"yesterday's matters\" (things to learn from)"}],"type":"paragraph"}],"spread":false,"type":"listItem"},{"checked":null,"children":[{"children":[{"children":[{"type":"text","value":"总结昨天"}],"type":"strong"},{"type":"text","value":" (zǒngjié zuótiān) - \"summarize yesterday\" (reflection practice)"}],"type":"paragraph"}],"spread":false,"type":"listItem"},{"checked":null,"children":[{"children":[{"children":[{"type":"text","value":"昨天的教训"}],"type":"strong"},{"type":"text","value":" (zuótiān de jiàoxùn) - \"yesterday's lesson\""}],"type":"paragraph"}],"spread":false,"type":"listItem"}],"ordered":false,"spread":false,"start":null,"type":"list"},
    {"children":[{"children":[{"type":"text","value":"Philosophy of Time:"}],"type":"strong"}],"type":"paragraph"},
    {"children":[{"checked":null,"children":[{"children":[{"children":[{"type":"text","value":"昨天已过"}],"type":"strong"},{"type":"text","value":" (zuótiān yǐ guò) - \"yesterday has passed\" (move forward)"}],"type":"paragraph"}],"spread":false,"type":"listItem"},{"checked":null,"children":[{"children":[{"children":[{"type":"text","value":"不悔昨天"}],"type":"strong"},{"type":"text","value":" (bù huǐ zuótiān) - \"don't regret yesterday\""}],"type":"paragraph"}],"spread":false,"type":"listItem"},{"checked":null,"children":[{"children":[{"children":[{"type":"text","value":"珍惜今天"}],"type":"strong"},{"type":"text","value":" (zhēnxī jīntiān) - \"treasure today\" (vs dwelling on yesterday)"}],"type":"paragraph"}],"spread":false,"type":"listItem"}],"ordered":false,"spread":false,"start":null,"type":"list"},
    {"children":[{"type":"text","value":"Planning and Memory"}],"depth":2,"type":"heading"},
    {"children":[{"type":"text","value":"昨天 in practical usage:"}],"type":"paragraph"},
    {"children":[{"checked":null,"children":[{"children":[{"children":[{"type":"text","value":"昨天的计划"}],"type":"strong"},{"type":"text","value":" (zuótiān de jìhuà) - \"yesterday's plan\""}],"type":"paragraph"}],"spread":false,"type":"listItem"},{"checked":null,"children":[{"children":[{"children":[{"type":"text","value":"昨天的会议"}],"type":"strong"},{"type":"text","value":" (zuótiān de huìyì) - \"yesterday's meeting\""}],"type":"paragraph"}],"spread":false,"type":"listItem"},{"checked":null,"children":[{"children":[{"children":[{"type":"text","value":"昨天的决定"}],"type":"strong"},{"type":"text","value":" (zuótiān de juédìng) - \"yesterday's decision\""}],"type":"paragraph"}],"spread":false,"type":"listItem"},{"checked":null,"children":[{"children":[{"children":[{"type":"text","value":"记得昨天"}],"type":"strong"},{"type":"text","value":" (jìde zuótiān) - \"remember yesterday\""}],"type":"paragraph"}],"spread":false,"type":"listItem"}],"ordered":false,"spread":false,"start":null,"type":"list"},
    {"children":[{"type":"text","value":"Common Expressions"}],"depth":2,"type":"heading"},
    {"children":[{"checked":null,"children":[{"children":[{"children":[{"type":"text","value":"昨日重现"}],"type":"strong"},{"type":"text","value":" (zuórì chóngxiàn) - \"yesterday once more\""}],"type":"paragraph"}],"spread":false,"type":"listItem"},{"checked":null,"children":[{"children":[{"children":[{"type":"text","value":"昨天的我"}],"type":"strong"},{"type":"text","value":" (zuótiān de wǒ) - \"yesterday's me\" (past self)"}],"type":"paragraph"}],"spread":false,"type":"listItem"},{"checked":null,"children":[{"children":[{"children":[{"type":"text","value":"如同昨天"}],"type":"strong"},{"type":"text","value":" (rútóng zuótiān) - \"as if it were yesterday\""}],"type":"paragraph"}],"spread":false,"type":"listItem"},{"checked":null,"children":[{"children":[{"children":[{"type":"text","value":"昨天的故事"}],"type":"strong"},{"type":"text","value":" (zuótiān de gùshi) - \"yesterday's story\""}],"type":"paragraph"}],"spread":false,"type":"listItem"}],"ordered":false,"spread":false,"start":null,"type":"list"},
    {"children":[{"type":"text","value":"Comparative Usage"}],"depth":2,"type":"heading"},
    {"children":[{"type":"text","value":"昨天 with other time words:"}],"type":"paragraph"},
    {"children":[{"checked":null,"children":[{"children":[{"children":[{"type":"text","value":"昨天、今天、明天"}],"type":"strong"},{"type":"text","value":" (zuótiān, jīntiān, míngtiān) - \"yesterday, today, tomorrow\""}],"type":"paragraph"}],"spread":false,"type":"listItem"},{"checked":null,"children":[{"children":[{"children":[{"type":"text","value":"昨天比今天"}],"type":"strong"},{"type":"text","value":" (zuótiān bǐ jīntiān) - \"yesterday compared to today\""}],"type":"paragraph"}],"spread":false,"type":"listItem"},{"checked":null,"children":[{"children":[{"children":[{"type":"text","value":"从昨天到今天"}],"type":"strong"},{"type":"text","value":" (cóng zuótiān dào jīntiān) - \"from yesterday to today\""}],"type":"paragraph"}],"spread":false,"type":"listItem"}],"ordered":false,"spread":false,"start":null,"type":"list"},
    {"children":[{"type":"text","value":"Work and Schedule"}],"depth":2,"type":"heading"},
    {"children":[{"type":"text","value":"昨天 in professional context:"}],"type":"paragraph"},
    {"children":[{"checked":null,"children":[{"children":[{"children":[{"type":"text","value":"昨天上班"}],"type":"strong"},{"type":"text","value":" (zuótiān shàngbān) - \"worked yesterday\""}],"type":"paragraph"}],"spread":false,"type":"listItem"},{"checked":null,"children":[{"children":[{"children":[{"type":"text","value":"昨天休息"}],"type":"strong"},{"type":"text","value":" (zuótiān xiūxi) - \"rested yesterday\""}],"type":"paragraph"}],"spread":false,"type":"listItem"},{"checked":null,"children":[{"children":[{"children":[{"type":"text","value":"昨天出差"}],"type":"strong"},{"type":"text","value":" (zuótiān chūchāi) - \"business trip yesterday\""}],"type":"paragraph"}],"spread":false,"type":"listItem"},{"checked":null,"children":[{"children":[{"children":[{"type":"text","value":"昨天开会"}],"type":"strong"},{"type":"text","value":" (zuótiān kāihuì) - \"had a meeting yesterday\""}],"type":"paragraph"}],"spread":false,"type":"listItem"}],"ordered":false,"spread":false,"start":null,"type":"list"},
    {"children":[{"type":"text","value":"Weather and Conditions"}],"depth":2,"type":"heading"},
    {"children":[{"type":"text","value":"昨天 describing past conditions:"}],"type":"paragraph"},
    {"children":[{"checked":null,"children":[{"children":[{"children":[{"type":"text","value":"昨天天气"}],"type":"strong"},{"type":"text","value":" (zuótiān tiānqì) - \"yesterday's weather\""}],"type":"paragraph"}],"spread":false,"type":"listItem"},{"checked":null,"children":[{"children":[{"children":[{"type":"text","value":"昨天很热"}],"type":"strong"},{"type":"text","value":" (zuótiān hěn rè) - \"yesterday was hot\""}],"type":"paragraph"}],"spread":false,"type":"listItem"},{"checked":null,"children":[{"children":[{"children":[{"type":"text","value":"昨天下雪"}],"type":"strong"},{"type":"text","value":" (zuótiān xiàxuě) - \"it snowed yesterday\""}],"type":"paragraph"}],"spread":false,"type":"listItem"}],"ordered":false,"spread":false,"start":null,"type":"list"},
    {"children":[{"type":"text","value":"Grammar Functions"}],"depth":2,"type":"heading"},
    {"children":[{"checked":null,"children":[{"children":[{"children":[{"type":"text","value":"Time adverb"}],"type":"strong"},{"type":"text","value":": 昨天我去了 (zuótiān wǒ qù le) - \"yesterday I went\""}],"type":"paragraph"}],"spread":false,"type":"listItem"},{"checked":null,"children":[{"children":[{"children":[{"type":"text","value":"Noun modifier"}],"type":"strong"},{"type":"text","value":": 昨天的新闻 (zuótiān de xīnwén) - \"yesterday's news\""}],"type":"paragraph"}],"spread":false,"type":"listItem"},{"checked":null,"children":[{"children":[{"children":[{"type":"text","value":"Time frame"}],"type":"strong"},{"type":"text","value":": 从昨天起 (cóng zuótiān qǐ) - \"starting from yesterday\""}],"type":"paragraph"}],"spread":false,"type":"listItem"}],"ordered":false,"spread":false,"start":null,"type":"list"},
    {"children":[{"type":"text","value":"Learning Notes"}],"depth":2,"type":"heading"},
    {"children":[{"type":"text","value":"昨天 is essential because:"}],"type":"paragraph"},
    {"children":[{"checked":null,"children":[{"children":[{"type":"text","value":"Fundamental time word for expressing immediate past"}],"type":"paragraph"}],"spread":false,"type":"listItem"},{"checked":null,"children":[{"children":[{"type":"text","value":"Essential for narrating recent events and experiences"}],"type":"paragraph"}],"spread":false,"type":"listItem"},{"checked":null,"children":[{"children":[{"type":"text","value":"Key to understanding Chinese temporal thinking and planning"}],"type":"paragraph"}],"spread":false,"type":"listItem"},{"checked":null,"children":[{"children":[{"type":"text","value":"Important for daily conversation and scheduling"}],"type":"paragraph"}],"spread":false,"type":"listItem"},{"checked":null,"children":[{"children":[{"type":"text","value":"Demonstrates the Chinese emphasis on learning from recent experience"}],"type":"paragraph"}],"spread":false,"type":"listItem"}],"ordered":false,"spread":false,"start":null,"type":"list"},
    {"children":[{"type":"text","value":"昨天 reflects the Chinese understanding that the immediate past is both a completed cycle to learn\nfrom and a foundation for understanding today's opportunities and tomorrow's possibilities!"}],"type":"paragraph"}
  ],
  "type":"root"
}