{
  "children":[
    {"children":[{"type":"text","value":"Core Meaning & Usage"}],"depth":2,"type":"heading"},
    {"children":[{"type":"text","value":"母 represents "},{"children":[{"type":"text","value":"the concept of motherhood and maternal relationships"}],"type":"strong"},{"type":"text","value":":"}],"type":"paragraph"},
    {"children":[{"checked":null,"children":[{"children":[{"children":[{"type":"text","value":"Family"}],"type":"strong"},{"type":"text","value":": \"母亲\" (mǔ qīn) - \"mother\" (formal)"}],"type":"paragraph"}],"spread":false,"type":"listItem"},{"checked":null,"children":[{"children":[{"children":[{"type":"text","value":"Origin"}],"type":"strong"},{"type":"text","value":": \"母语\" (mǔ yǔ) - \"mother tongue; native language\""}],"type":"paragraph"}],"spread":false,"type":"listItem"},{"checked":null,"children":[{"children":[{"children":[{"type":"text","value":"Source"}],"type":"strong"},{"type":"text","value":": \"母校\" (mǔ xiào) - \"alma mater\" (mother school)"}],"type":"paragraph"}],"spread":false,"type":"listItem"},{"checked":null,"children":[{"children":[{"children":[{"type":"text","value":"Animals"}],"type":"strong"},{"type":"text","value":": \"母鸡\" (mǔ jī) - \"hen\" (female chicken)"}],"type":"paragraph"}],"spread":false,"type":"listItem"}],"ordered":true,"spread":false,"start":1,"type":"list"},
    {"children":[{"type":"text","value":"Examples"}],"depth":2,"type":"heading"},
    {"children":[{"checked":null,"children":[{"children":[{"children":[{"type":"text","value":"母子"}],"type":"strong"},{"type":"text","value":" (mǔ zǐ) - \"mother and child\""}],"type":"paragraph"}],"spread":false,"type":"listItem"},{"checked":null,"children":[{"children":[{"children":[{"type":"text","value":"母爱"}],"type":"strong"},{"type":"text","value":" (mǔ ài) - \"maternal love\""}],"type":"paragraph"}],"spread":false,"type":"listItem"},{"checked":null,"children":[{"children":[{"children":[{"type":"text","value":"祖母"}],"type":"strong"},{"type":"text","value":" (zǔ mǔ) - \"grandmother\" (paternal)"}],"type":"paragraph"}],"spread":false,"type":"listItem"},{"checked":null,"children":[{"children":[{"children":[{"type":"text","value":"母国"}],"type":"strong"},{"type":"text","value":" (mǔ guó) - \"motherland; native country\""}],"type":"paragraph"}],"spread":false,"type":"listItem"},{"checked":null,"children":[{"children":[{"children":[{"type":"text","value":"母亲节"}],"type":"strong"},{"type":"text","value":" (mǔ qīn jiē) - \"Mother's Day\""}],"type":"paragraph"}],"spread":false,"type":"listItem"}],"ordered":false,"spread":false,"start":null,"type":"list"},
    {"children":[{"type":"text","value":"Cultural Context"}],"depth":2,"type":"heading"},
    {"children":[{"type":"text","value":"母 holds profound significance in Chinese culture, representing not just biological motherhood but\nthe source of life, wisdom, and cultural transmission. The concept extends to describe origins and\nfoundations - one's \"mother\" language, school, or country. Maternal respect and filial piety toward\nmothers are cornerstone values in Chinese society."}],"type":"paragraph"}
  ],
  "type":"root"
}